jupyterlab_email/__init__.py
jupyterlab_email/_email.py
jupyterlab_email/_version.py
jupyterlab_email/attachments.py
jupyterlab_email/extension.py
jupyterlab_email/handlers.py
jupyterlab_email/nbconvert.py
jupyterlab_email/postprocessors.py
jupyterlab_email/extension/install.json
jupyterlab_email/extension/jupyterlab_email.json
jupyterlab_email/labextension/package.json
jupyterlab_email/labextension/static/568.ac63c76961b827074813.js
jupyterlab_email/labextension/static/873.2936191629e6b9994ac7.js
jupyterlab_email/labextension/static/remoteEntry.d54b833a0b966a906cf4.js
jupyterlab_email/labextension/static/style.js
jupyterlab_email/labextension/static/third-party-licenses.json
jupyterlab_email/templates/error.tpl
jupyterlab_email/templates/hide_code_cells_html.tpl
jupyterlab_email/templates/hide_code_cells_html_email.tpl
jupyterlab_email/templates/hide_code_cells_pdf.tplx
jupyterlab_email/templates/html.tpl
jupyterlab_email/templates/html_email.tpl
jupyterlab_email/templates/pdf.tplx
jupyterlab_email/templates/pdf_license
jupyterlab_email/tests/__init__.py
jupyterlab_email/tests/test_extension.py
jupyterlab_email/tests/test_init.py
jupyterlab_email-0.3.1.data/data/etc/jupyter/jupyter_server_config.d/jupyterlab_email.json
jupyterlab_email-0.3.1.data/data/share/jupyter/labextensions/jupyterlab_email/package.json
jupyterlab_email-0.3.1.data/data/share/jupyter/labextensions/jupyterlab_email/static/568.ac63c76961b827074813.js
jupyterlab_email-0.3.1.data/data/share/jupyter/labextensions/jupyterlab_email/static/873.2936191629e6b9994ac7.js
jupyterlab_email-0.3.1.data/data/share/jupyter/labextensions/jupyterlab_email/static/remoteEntry.d54b833a0b966a906cf4.js
jupyterlab_email-0.3.1.data/data/share/jupyter/labextensions/jupyterlab_email/static/style.js
jupyterlab_email-0.3.1.data/data/share/jupyter/labextensions/jupyterlab_email/static/third-party-licenses.json
jupyterlab_email-0.3.1.data/data/share/jupyter/labextensions/jupyterlab_email/install.json
jupyterlab_email-0.3.1.dist-info/METADATA
jupyterlab_email-0.3.1.dist-info/WHEEL
jupyterlab_email-0.3.1.dist-info/licenses/LICENSE
jupyterlab_email-0.3.1.dist-info/RECORD
