Metadata-Version: 2.1
Name: jupyterlab_email
Version: 0.3.1
Summary: Sending emails from JupyterLab
Project-URL: Repository, https://github.com/timkpaine/jupyterlab_email
Project-URL: Homepage, https://github.com/timkpaine/jupyterlab_email
Author: the jupyterlab_email authors
License:                                  Apache License
License-File: LICENSE
Keywords: Jupyter,JupyterLab,Templates
Classifier: Development Status :: 4 - Beta
Classifier: Framework :: Jupyter
Classifier: Framework :: Jupyter :: JupyterLab
Classifier: License :: OSI Approved :: Apache Software License
Classifier: Programming Language :: Python
Classifier: Programming Language :: Python :: 3
Classifier: Programming Language :: Python :: 3.7
Classifier: Programming Language :: Python :: 3.8
Classifier: Programming Language :: Python :: 3.9
Classifier: Programming Language :: Python :: 3.10
Classifier: Programming Language :: Python :: 3.11
Requires-Python: >=3.7
Requires-Dist: beautifulsoup4>=4.9.1
Requires-Dist: emails>=0.5.15
Requires-Dist: ipython>=7.2.0
Requires-Dist: jupyterlab<5,>=4
Requires-Dist: pandas>=0.23.4
Requires-Dist: python-magic>=0.4.15
Provides-Extra: develop
Requires-Dist: black>=23; extra == 'develop'
Requires-Dist: check-manifest; extra == 'develop'
Requires-Dist: pytest; extra == 'develop'
Requires-Dist: pytest-cov; extra == 'develop'
Requires-Dist: ruff; extra == 'develop'
Provides-Extra: test
Requires-Dist: pytest; extra == 'test'
Requires-Dist: pytest-cov; extra == 'test'
